docster/__init__.py
docster/helpers.py
docster/main.py
docster/models.py
docster/py.typed
docster/visitor.py
docster-0.1.6.dist-info/entry_points.txt
docster-0.1.6.dist-info/LICENSE
docster-0.1.6.dist-info/WHEEL
docster-0.1.6.dist-info/METADATA
docster-0.1.6.dist-info/RECORD
